byted_overpass_flow_fpa_news_event_rank_service/__init__.py
byted_overpass_flow_fpa_news_event_rank_service-0.0.1.dist-info/METADATA
byted_overpass_flow_fpa_news_event_rank_service-0.0.1.dist-info/WHEEL
byted_overpass_flow_fpa_news_event_rank_service-0.0.1.dist-info/top_level.txt
byted_overpass_flow_fpa_news_event_rank_service-0.0.1.dist-info/RECORD
